{
  "year": 2026,
  "races": [
    {
      "round": 1,
      "name": "Australian Grand Prix Qualifying",
      "shortName": "AUS-Q",
      "date": "2026-03-7",
      "type": "qualifying",
      "circuit": "Albert Park Circuit",
      "location": "Melbourne, Australia"
    },
    {
      "round": 2,
      "name": "Australian Grand Prix",
      "shortName": "AUS",
      "date": "2026-03-8",
      "type": "race",
      "circuit": "Albert Park Circuit",
      "location": "Melbourne, Australia"
    },
    {
      "round": 3,
      "name": "Chinese Grand Prix Sprint Qualifying",
      "shortName": "CHN-SQ",
      "date": "2026-03-13",
      "type": "qualifying",
      "circuit": "Shanghai International Circuit",
      "location": "Shanghai, China"
    },
    {
      "round": 4,
      "name": "Chinese Grand Prix Sprint",
      "shortName": "CHN-S",
      "date": "2026-03-14",
      "type": "sprint",
      "circuit": "Shanghai International Circuit",
      "location": "Shanghai, China"
    },
    {
      "round": 5,
      "name": "Chinese Grand Prix Qualifying",
      "shortName": "CHN-Q",
      "date": "2026-03-14",
      "type": "qualifying",
      "circuit": "Shanghai International Circuit",
      "location": "Shanghai, China"
    },
    {
      "round": 6,
      "name": "Chinese Grand Prix",
      "shortName": "CHN",
      "date": "2026-03-15",
      "type": "race",
      "circuit": "Shanghai International Circuit",
      "location": "Shanghai, China"
    },
    {
      "round": 7,
      "name": "Japan Grand Prix Qualifying",
      "shortName": "JPN-Q",
      "date": "2026-03-29",
      "type": "qualifying",
      "circuit": "Suzuka International Racing Course",
      "location": "Suzuka, Japan"
    },
    {
      "round": 8,
      "name": "Japan Grand Prix",
      "shortName": "JPN",
      "date": "2026-03-29",
      "type": "race",
      "circuit": "Suzuka International Racing Course",
      "location": "Suzuka, Japan"
    }
  ],
  "raceDetails": [
    {
      "round": 1,
      "qualifyingResults": [
        {
          "position": 1,
          "driverNumber": 63,
          "driverId": "RUS",
          "driver": "George Russell",
          "team": "Mercedes",
          "q1": "1:19.507",
          "q2": "1:18.934",
          "q3": "1:18.518",
          "laps": 22
        },
        {
          "position": 2,
          "driverNumber": 12,
          "driverId": "ANT",
          "driver": "Kimi Antonelli",
          "team": "Mercedes",
          "q1": "1:20.120",
          "q2": "1:19.435",
          "q3": "1:18.811",
          "laps": 18
        },
        {
          "position": 3,
          "driverNumber": 6,
          "driverId": "HAD",
          "driver": "Isack Hadjar",
          "team": "Red Bull Racing",
          "q1": "1:20.023",
          "q2": "1:19.653",
          "q3": "1:19.303",
          "laps": 19
        },
        {
          "position": 4,
          "driverNumber": 16,
          "driverId": "LEC",
          "driver": "Charles Leclerc",
          "team": "Ferrari",
          "q1": "1:20.226",
          "q2": "1:19.357",
          "q3": "1:19.327",
          "laps": 24
        },
        {
          "position": 5,
          "driverNumber": 81,
          "driverId": "PIA",
          "driver": "Oscar Piastri",
          "team": "McLaren",
          "q1": "1:19.664",
          "q2": "1:19.525",
          "q3": "1:19.380",
          "laps": 26
        },
        {
          "position": 6,
          "driverNumber": 1,
          "driverId": "NOR",
          "driver": "Lando Norris",
          "team": "McLaren",
          "q1": "1:20.010",
          "q2": "1:19.882",
          "q3": "1:19.475",
          "laps": 26
        },
        {
          "position": 7,
          "driverNumber": 44,
          "driverId": "HAM",
          "driver": "Lewis Hamilton",
          "team": "Ferrari",
          "q1": "1:19.811",
          "q2": "1:19.921",
          "q3": "1:19.478",
          "laps": 25
        },
        {
          "position": 8,
          "driverNumber": 30,
          "driverId": "LAW",
          "driver": "Liam Lawson",
          "team": "Racing Bulls",
          "q1": "1:20.491",
          "q2": "1:20.144",
          "q3": "1:19.994",
          "laps": 24
        },
        {
          "position": 9,
          "driverNumber": 41,
          "driverId": "LIN",
          "driver": "Arvid Lindblad",
          "team": "Racing Bulls",
          "q1": "1:20.409",
          "q2": "1:19.971",
          "q3": "1:21.247",
          "laps": 25
        },
        {
          "position": 10,
          "driverNumber": 5,
          "driverId": "BOR",
          "driver": "Gabriel Bortoleto",
          "team": "Sauber",
          "q1": "1:20.495",
          "q2": "1:20.221",
          "q3": null,
          "laps": 14
        },
        {
          "position": 11,
          "driverNumber": 27,
          "driverId": "HUL",
          "driver": "Nico Hulkenberg",
          "team": "Sauber",
          "q1": "1:21.024",
          "q2": "1:20.303",
          "q3": null,
          "laps": 18
        },
        {
          "position": 12,
          "driverNumber": 87,
          "driverId": "BEA",
          "driver": "Oliver Bearman",
          "team": "Haas",
          "q1": "1:21.247",
          "q2": "1:20.311",
          "q3": null,
          "laps": 18
        },
        {
          "position": 13,
          "driverNumber": 31,
          "driverId": "OCO",
          "driver": "Esteban Ocon",
          "team": "Haas",
          "q1": "1:20.759",
          "q2": "1:20.491",
          "q3": null,
          "laps": 18
        },
        {
          "position": 14,
          "driverNumber": 10,
          "driverId": "GAS",
          "driver": "Pierre Gasly",
          "team": "Alpine",
          "q1": "1:21.138",
          "q2": "1:20.501",
          "q3": null,
          "laps": 18
        },
        {
          "position": 15,
          "driverNumber": 23,
          "driverId": "ALB",
          "driver": "Alexander Albon",
          "team": "Williams",
          "q1": "1:21.051",
          "q2": "1:20.941",
          "q3": null,
          "laps": 19
        },
        {
          "position": 16,
          "driverNumber": 43,
          "driverId": "COL",
          "driver": "Franco Colapinto",
          "team": "Alpine",
          "q1": "1:21.200",
          "q2": "1:21.270",
          "q3": null,
          "laps": 18
        },
        {
          "position": 17,
          "driverNumber": 14,
          "driverId": "ALO",
          "driver": "Fernando Alonso",
          "team": "Aston Martin",
          "q1": "1:21.969",
          "q2": null,
          "q3": null,
          "laps": 10
        },
        {
          "position": 18,
          "driverNumber": 11,
          "driverId": "PER",
          "driver": "Sergio Perez",
          "team": "Cadillac",
          "q1": "1:22.605",
          "q2": null,
          "q3": null,
          "laps": 7
        },
        {
          "position": 19,
          "driverNumber": 77,
          "driverId": "BOT",
          "driver": "Valtteri Bottas",
          "team": "Cadillac",
          "q1": "1:23.244",
          "q2": null,
          "q3": null,
          "laps": 8
        }
      ]
    },
    {
      "round": 2,
      "raceResults": [
        {
          "position": 1,
          "driverNumber": 63,
          "driverId": "RUS",
          "driver": "George Russell",
          "team": "Mercedes",
          "startingGrid": 1,
          "laps": 58,
          "time": "1:23:06.801",
          "points": 25,
          "fastestLapTime": "1:22.670"
        },
        {
          "position": 2,
          "driverNumber": 12,
          "driverId": "ANT",
          "driver": "Kimi Antonelli",
          "team": "Mercedes",
          "startingGrid": 2,
          "laps": 58,
          "time": "+2.974",
          "points": 18,
          "fastestLapTime": "1:22.417"
        },
        {
          "position": 3,
          "driverNumber": 16,
          "driverId": "LEC",
          "driver": "Charles Leclerc",
          "team": "Ferrari",
          "startingGrid": 4,
          "laps": 58,
          "time": "+15.519",
          "points": 15,
          "fastestLapTime": "1:22.579"
        },
        {
          "position": 4,
          "driverNumber": 44,
          "driverId": "HAM",
          "driver": "Lewis Hamilton",
          "team": "Ferrari",
          "startingGrid": 7,
          "laps": 58,
          "time": "+16.144",
          "points": 12,
          "fastestLapTime": "1:22.423"
        },
        {
          "position": 5,
          "driverNumber": 1,
          "driverId": "NOR",
          "driver": "Lando Norris",
          "team": "McLaren",
          "startingGrid": 6,
          "laps": 58,
          "time": "+51.741",
          "points": 10,
          "fastestLapTime": "1:22.358"
        },
        {
          "position": 6,
          "driverNumber": 3,
          "driverId": "VER",
          "driver": "Max Verstappen",
          "team": "Red Bull Racing",
          "startingGrid": 20,
          "laps": 58,
          "time": "+54.617",
          "points": 8,
          "setFastestLap": true,
          "fastestLapTime": "1:22.091"
        },
        {
          "position": 7,
          "driverNumber": 87,
          "driverId": "BEA",
          "driver": "Oliver Bearman",
          "team": "Haas",
          "startingGrid": 12,
          "laps": 57,
          "time": "+1 lap",
          "points": 6,
          "fastestLapTime": "1:24.020"
        },
        {
          "position": 8,
          "driverNumber": 41,
          "driverId": "LIN",
          "driver": "Arvid Lindblad",
          "team": "Racing Bulls",
          "startingGrid": 9,
          "laps": 57,
          "time": "+1 lap",
          "points": 4,
          "fastestLapTime": "1:24.182"
        },
        {
          "position": 9,
          "driverNumber": 5,
          "driverId": "BOR",
          "driver": "Gabriel Bortoleto",
          "team": "Sauber",
          "startingGrid": 10,
          "laps": 57,
          "time": "+1 lap",
          "points": 2,
          "fastestLapTime": "1:23.257"
        },
        {
          "position": 10,
          "driverNumber": 10,
          "driverId": "GAS",
          "driver": "Pierre Gasly",
          "team": "Alpine",
          "startingGrid": 14,
          "laps": 57,
          "time": "+1 lap",
          "points": 1,
          "fastestLapTime": "1:24.486"
        },
        {
          "position": 11,
          "driverNumber": 31,
          "driverId": "OCO",
          "driver": "Esteban Ocon",
          "team": "Haas",
          "startingGrid": 13,
          "laps": 57,
          "time": "+1 lap",
          "points": 0,
          "fastestLapTime": "1:24.424"
        },
        {
          "position": 12,
          "driverNumber": 23,
          "driverId": "ALB",
          "driver": "Alexander Albon",
          "team": "Williams",
          "startingGrid": 15,
          "laps": 57,
          "time": "+1 lap",
          "points": 0,
          "fastestLapTime": "1:24.375"
        },
        {
          "position": 13,
          "driverNumber": 30,
          "driverId": "LAW",
          "driver": "Liam Lawson",
          "team": "Racing Bulls",
          "startingGrid": 8,
          "laps": 57,
          "time": "+1 lap",
          "points": 0,
          "fastestLapTime": "1:23.783"
        },
        {
          "position": 14,
          "driverNumber": 43,
          "driverId": "COL",
          "driver": "Franco Colapinto",
          "team": "Alpine",
          "startingGrid": 16,
          "laps": 56,
          "time": "+2 laps",
          "points": 0,
          "fastestLapTime": "1:22.926"
        },
        {
          "position": 15,
          "driverNumber": 55,
          "driverId": "SAI",
          "driver": "Carlos Sainz",
          "team": "Williams",
          "startingGrid": 21,
          "laps": 56,
          "time": "+2 laps",
          "points": 0,
          "fastestLapTime": "1:23.590"
        },
        {
          "position": 16,
          "driverNumber": 11,
          "driverId": "PER",
          "driver": "Sergio Perez",
          "team": "Cadillac",
          "startingGrid": 18,
          "laps": 55,
          "time": "+3 laps",
          "points": 0,
          "fastestLapTime": "1:26.070"
        },
        {
          "position": 17,
          "driverNumber": 18,
          "driverId": "STR",
          "driver": "Lance Stroll",
          "team": "Aston Martin",
          "startingGrid": 22,
          "laps": 43,
          "time": "+15 laps",
          "points": 0,
          "fastestLapTime": "1:25.410",
          "status": "+15 laps"
        },
        {
          "position": 18,
          "driverNumber": 14,
          "driverId": "ALO",
          "driver": "Fernando Alonso",
          "team": "Aston Martin",
          "startingGrid": 17,
          "laps": 21,
          "time": "DNF",
          "points": 0,
          "fastestLapTime": "1:25.713",
          "status": "DNF"
        },
        {
          "position": 19,
          "driverNumber": 77,
          "driverId": "BOT",
          "driver": "Valtteri Bottas",
          "team": "Cadillac",
          "startingGrid": 19,
          "laps": 15,
          "time": "DNF",
          "points": 0,
          "fastestLapTime": "1:27.364",
          "status": "DNF"
        },
        {
          "position": 20,
          "driverNumber": 6,
          "driverId": "HAD",
          "driver": "Isack Hadjar",
          "team": "Red Bull Racing",
          "startingGrid": 3,
          "laps": 10,
          "time": "DNF",
          "points": 0,
          "fastestLapTime": "1:25.239",
          "status": "DNF"
        },
        {
          "position": 21,
          "driverNumber": 81,
          "driverId": "PIA",
          "driver": "Oscar Piastri",
          "team": "McLaren",
          "startingGrid": 5,
          "laps": 0,
          "time": "DNS",
          "points": 0,
          "status": "DNS"
        },
        {
          "position": 22,
          "driverNumber": 27,
          "driverId": "HUL",
          "driver": "Nico Hulkenberg",
          "team": "Sauber",
          "startingGrid": 11,
          "laps": 0,
          "time": "DNS",
          "points": 0,
          "status": "DNS"
        }
      ],
      "qualifyingResults": [
        {
          "position": 1,
          "driverNumber": 63,
          "driverId": "RUS",
          "driver": "George Russell",
          "team": "Mercedes",
          "q1": "1:19.507",
          "q2": "1:18.934",
          "q3": "1:18.518",
          "laps": 22
        },
        {
          "position": 2,
          "driverNumber": 12,
          "driverId": "ANT",
          "driver": "Kimi Antonelli",
          "team": "Mercedes",
          "q1": "1:20.120",
          "q2": "1:19.435",
          "q3": "1:18.811",
          "laps": 18
        },
        {
          "position": 3,
          "driverNumber": 6,
          "driverId": "HAD",
          "driver": "Isack Hadjar",
          "team": "Red Bull Racing",
          "q1": "1:20.023",
          "q2": "1:19.653",
          "q3": "1:19.303",
          "laps": 19
        },
        {
          "position": 4,
          "driverNumber": 16,
          "driverId": "LEC",
          "driver": "Charles Leclerc",
          "team": "Ferrari",
          "q1": "1:20.226",
          "q2": "1:19.357",
          "q3": "1:19.327",
          "laps": 24
        },
        {
          "position": 5,
          "driverNumber": 81,
          "driverId": "PIA",
          "driver": "Oscar Piastri",
          "team": "McLaren",
          "q1": "1:19.664",
          "q2": "1:19.525",
          "q3": "1:19.380",
          "laps": 26
        },
        {
          "position": 6,
          "driverNumber": 1,
          "driverId": "NOR",
          "driver": "Lando Norris",
          "team": "McLaren",
          "q1": "1:20.010",
          "q2": "1:19.882",
          "q3": "1:19.475",
          "laps": 26
        },
        {
          "position": 7,
          "driverNumber": 44,
          "driverId": "HAM",
          "driver": "Lewis Hamilton",
          "team": "Ferrari",
          "q1": "1:19.811",
          "q2": "1:19.921",
          "q3": "1:19.478",
          "laps": 25
        },
        {
          "position": 8,
          "driverNumber": 30,
          "driverId": "LAW",
          "driver": "Liam Lawson",
          "team": "Racing Bulls",
          "q1": "1:20.491",
          "q2": "1:20.144",
          "q3": "1:19.994",
          "laps": 24
        },
        {
          "position": 9,
          "driverNumber": 41,
          "driverId": "LIN",
          "driver": "Arvid Lindblad",
          "team": "Racing Bulls",
          "q1": "1:20.409",
          "q2": "1:19.971",
          "q3": "1:21.247",
          "laps": 25
        },
        {
          "position": 10,
          "driverNumber": 5,
          "driverId": "BOR",
          "driver": "Gabriel Bortoleto",
          "team": "Sauber",
          "q1": "1:20.495",
          "q2": "1:20.221",
          "q3": null,
          "laps": 14
        },
        {
          "position": 11,
          "driverNumber": 27,
          "driverId": "HUL",
          "driver": "Nico Hulkenberg",
          "team": "Sauber",
          "q1": "1:21.024",
          "q2": "1:20.303",
          "q3": null,
          "laps": 18
        },
        {
          "position": 12,
          "driverNumber": 87,
          "driverId": "BEA",
          "driver": "Oliver Bearman",
          "team": "Haas",
          "q1": "1:21.247",
          "q2": "1:20.311",
          "q3": null,
          "laps": 18
        },
        {
          "position": 13,
          "driverNumber": 31,
          "driverId": "OCO",
          "driver": "Esteban Ocon",
          "team": "Haas",
          "q1": "1:20.759",
          "q2": "1:20.491",
          "q3": null,
          "laps": 18
        },
        {
          "position": 14,
          "driverNumber": 10,
          "driverId": "GAS",
          "driver": "Pierre Gasly",
          "team": "Alpine",
          "q1": "1:21.138",
          "q2": "1:20.501",
          "q3": null,
          "laps": 18
        },
        {
          "position": 15,
          "driverNumber": 23,
          "driverId": "ALB",
          "driver": "Alexander Albon",
          "team": "Williams",
          "q1": "1:21.051",
          "q2": "1:20.941",
          "q3": null,
          "laps": 19
        },
        {
          "position": 16,
          "driverNumber": 43,
          "driverId": "COL",
          "driver": "Franco Colapinto",
          "team": "Alpine",
          "q1": "1:21.200",
          "q2": "1:21.270",
          "q3": null,
          "laps": 18
        },
        {
          "position": 17,
          "driverNumber": 14,
          "driverId": "ALO",
          "driver": "Fernando Alonso",
          "team": "Aston Martin",
          "q1": "1:21.969",
          "q2": null,
          "q3": null,
          "laps": 10
        },
        {
          "position": 18,
          "driverNumber": 11,
          "driverId": "PER",
          "driver": "Sergio Perez",
          "team": "Cadillac",
          "q1": "1:22.605",
          "q2": null,
          "q3": null,
          "laps": 7
        },
        {
          "position": 19,
          "driverNumber": 77,
          "driverId": "BOT",
          "driver": "Valtteri Bottas",
          "team": "Cadillac",
          "q1": "1:23.244",
          "q2": null,
          "q3": null,
          "laps": 8
        }
      ]
    },
    {
      "round": 3,
      "sprintQualifyingResults": [
        {
          "position": 1,
          "driverNumber": 63,
          "driverId": "RUS",
          "driver": "George Russell",
          "team": "Mercedes",
          "q1": "1:31.520",
          "q2": null,
          "q3": null,
          "laps": 0
        },
        {
          "position": 2,
          "driverNumber": 12,
          "driverId": "ANT",
          "driver": "Kimi Antonelli",
          "team": "Mercedes",
          "q1": "1:31.809",
          "q2": null,
          "q3": null,
          "laps": 0
        },
        {
          "position": 3,
          "driverNumber": 1,
          "driverId": "NOR",
          "driver": "Lando Norris",
          "team": "McLaren",
          "q1": "1:32.141",
          "q2": null,
          "q3": null,
          "laps": 0
        },
        {
          "position": 4,
          "driverNumber": 44,
          "driverId": "HAM",
          "driver": "Lewis Hamilton",
          "team": "Ferrari",
          "q1": "1:32.161",
          "q2": null,
          "q3": null,
          "laps": 0
        },
        {
          "position": 5,
          "driverNumber": 81,
          "driverId": "PIA",
          "driver": "Oscar Piastri",
          "team": "McLaren",
          "q1": "1:32.224",
          "q2": null,
          "q3": null,
          "laps": 0
        },
        {
          "position": 6,
          "driverNumber": 16,
          "driverId": "LEC",
          "driver": "Charles Leclerc",
          "team": "Ferrari",
          "q1": "1:32.528",
          "q2": null,
          "q3": null,
          "laps": 0
        },
        {
          "position": 7,
          "driverNumber": 10,
          "driverId": "GAS",
          "driver": "Pierre Gasly",
          "team": "Alpine",
          "q1": "1:32.888",
          "q2": null,
          "q3": null,
          "laps": 0
        },
        {
          "position": 8,
          "driverNumber": 3,
          "driverId": "VER",
          "driver": "Max Verstappen",
          "team": "Red Bull Racing",
          "q1": "1:33.254",
          "q2": null,
          "q3": null,
          "laps": 0
        },
        {
          "position": 9,
          "driverNumber": 87,
          "driverId": "BEA",
          "driver": "Oliver Bearman",
          "team": "Haas",
          "q1": "1:33.409",
          "q2": null,
          "q3": null,
          "laps": 0
        },
        {
          "position": 10,
          "driverNumber": 6,
          "driverId": "HAD",
          "driver": "Isack Hadjar",
          "team": "Red Bull Racing",
          "q1": "1:33.723",
          "q2": null,
          "q3": null,
          "laps": 0
        },
        {
          "position": 11,
          "driverNumber": 27,
          "driverId": "HUL",
          "driver": "Nico Hulkenberg",
          "team": "Sauber",
          "q1": "1:33.635",
          "q2": null,
          "q3": null,
          "laps": 0
        },
        {
          "position": 12,
          "driverNumber": 31,
          "driverId": "OCO",
          "driver": "Esteban Ocon",
          "team": "Haas",
          "q1": "1:33.639",
          "q2": null,
          "q3": null,
          "laps": 0
        },
        {
          "position": 13,
          "driverNumber": 30,
          "driverId": "LAW",
          "driver": "Liam Lawson",
          "team": "Racing Bulls",
          "q1": "1:33.714",
          "q2": null,
          "q3": null,
          "laps": 0
        },
        {
          "position": 14,
          "driverNumber": 5,
          "driverId": "BOR",
          "driver": "Gabriel Bortoleto",
          "team": "Sauber",
          "q1": "1:33.774",
          "q2": null,
          "q3": null,
          "laps": 0
        },
        {
          "position": 15,
          "driverNumber": 41,
          "driverId": "LIN",
          "driver": "Arvid Lindblad",
          "team": "Racing Bulls",
          "q1": "1:34.048",
          "q2": null,
          "q3": null,
          "laps": 0
        },
        {
          "position": 16,
          "driverNumber": 43,
          "driverId": "COL",
          "driver": "Franco Colapinto",
          "team": "Alpine",
          "q1": "1:34.327",
          "q2": null,
          "q3": null,
          "laps": 0
        },
        {
          "position": 17,
          "driverNumber": 55,
          "driverId": "SAI",
          "driver": "Carlos Sainz",
          "team": "Williams",
          "q1": "1:34.761",
          "q2": null,
          "q3": null,
          "laps": 0
        },
        {
          "position": 18,
          "driverNumber": 14,
          "driverId": "ALO",
          "driver": "Fernando Alonso",
          "team": "Aston Martin",
          "q1": "1:35.581",
          "q2": null,
          "q3": null,
          "laps": 0
        },
        {
          "position": 19,
          "driverNumber": 18,
          "driverId": "STR",
          "driver": "Lance Stroll",
          "team": "Aston Martin",
          "q1": "1:36.151",
          "q2": null,
          "q3": null,
          "laps": 0
        },
        {
          "position": 20,
          "driverNumber": 77,
          "driverId": "BOT",
          "driver": "Valtteri Bottas",
          "team": "Cadillac",
          "q1": "1:37.378",
          "q2": null,
          "q3": null,
          "laps": 0
        },
        {
          "position": 21,
          "driverNumber": 11,
          "driverId": "PER",
          "driver": "Sergio Perez",
          "team": "Cadillac",
          "q1": null,
          "q2": null,
          "q3": null,
          "laps": 0
        },
        {
          "position": 22,
          "driverNumber": 23,
          "driverId": "ALB",
          "driver": "Alexander Albon",
          "team": "Williams",
          "q1": "1:35.305",
          "q2": null,
          "q3": null,
          "laps": 0
        }
      ]
    },
    {
      "round": 4,
      "sprintResults": [
        {
          "position": 1,
          "driverNumber": 63,
          "driverId": "RUS",
          "driver": "George Russell",
          "team": "Mercedes",
          "startingGrid": null,
          "laps": 19,
          "time": "33:38.998",
          "points": 8
        },
        {
          "position": 2,
          "driverNumber": 16,
          "driverId": "LEC",
          "driver": "Charles Leclerc",
          "team": "Ferrari",
          "startingGrid": null,
          "laps": 19,
          "time": "+0.674",
          "points": 7
        },
        {
          "position": 3,
          "driverNumber": 44,
          "driverId": "HAM",
          "driver": "Lewis Hamilton",
          "team": "Ferrari",
          "startingGrid": null,
          "laps": 19,
          "time": "+2.554",
          "points": 6
        },
        {
          "position": 4,
          "driverNumber": 1,
          "driverId": "NOR",
          "driver": "Lando Norris",
          "team": "McLaren",
          "startingGrid": null,
          "laps": 19,
          "time": "+4.433",
          "points": 5
        },
        {
          "position": 5,
          "driverNumber": 12,
          "driverId": "ANT",
          "driver": "Kimi Antonelli",
          "team": "Mercedes",
          "startingGrid": null,
          "laps": 19,
          "time": "+5.688",
          "points": 4
        },
        {
          "position": 6,
          "driverNumber": 81,
          "driverId": "PIA",
          "driver": "Oscar Piastri",
          "team": "McLaren",
          "startingGrid": null,
          "laps": 19,
          "time": "+6.809",
          "points": 3
        },
        {
          "position": 7,
          "driverNumber": 30,
          "driverId": "LAW",
          "driver": "Liam Lawson",
          "team": "Racing Bulls",
          "startingGrid": null,
          "laps": 19,
          "time": "+10.900",
          "points": 2
        },
        {
          "position": 8,
          "driverNumber": 87,
          "driverId": "BEA",
          "driver": "Oliver Bearman",
          "team": "Haas",
          "startingGrid": null,
          "laps": 19,
          "time": "+11.271",
          "points": 1
        },
        {
          "position": 9,
          "driverNumber": 3,
          "driverId": "VER",
          "driver": "Max Verstappen",
          "team": "Red Bull Racing",
          "startingGrid": null,
          "laps": 19,
          "time": "+11.619",
          "points": 0
        },
        {
          "position": 10,
          "driverNumber": 31,
          "driverId": "OCO",
          "driver": "Esteban Ocon",
          "team": "Haas",
          "startingGrid": null,
          "laps": 19,
          "time": "+13.887",
          "points": 0
        },
        {
          "position": 11,
          "driverNumber": 10,
          "driverId": "GAS",
          "driver": "Pierre Gasly",
          "team": "Alpine",
          "startingGrid": null,
          "laps": 19,
          "time": "+14.780",
          "points": 0
        },
        {
          "position": 12,
          "driverNumber": 55,
          "driverId": "SAI",
          "driver": "Carlos Sainz",
          "team": "Williams",
          "startingGrid": null,
          "laps": 19,
          "time": "+15.753",
          "points": 0
        },
        {
          "position": 13,
          "driverNumber": 5,
          "driverId": "BOR",
          "driver": "Gabriel Bortoleto",
          "team": "Sauber",
          "startingGrid": null,
          "laps": 19,
          "time": "+15.858",
          "points": 0
        },
        {
          "position": 14,
          "driverNumber": 43,
          "driverId": "COL",
          "driver": "Franco Colapinto",
          "team": "Alpine",
          "startingGrid": null,
          "laps": 19,
          "time": "+16.393",
          "points": 0
        },
        {
          "position": 15,
          "driverNumber": 6,
          "driverId": "HAD",
          "driver": "Isack Hadjar",
          "team": "Red Bull Racing",
          "startingGrid": null,
          "laps": 19,
          "time": "+16.430",
          "points": 0
        },
        {
          "position": 16,
          "driverNumber": 23,
          "driverId": "ALB",
          "driver": "Alexander Albon",
          "team": "Williams",
          "startingGrid": null,
          "laps": 19,
          "time": "+20.014",
          "points": 0
        },
        {
          "position": 17,
          "driverNumber": 14,
          "driverId": "ALO",
          "driver": "Fernando Alonso",
          "team": "Aston Martin",
          "startingGrid": null,
          "laps": 19,
          "time": "+21.599",
          "points": 0
        },
        {
          "position": 18,
          "driverNumber": 18,
          "driverId": "STR",
          "driver": "Lance Stroll",
          "team": "Aston Martin",
          "startingGrid": null,
          "laps": 19,
          "time": "+21.971",
          "points": 0
        },
        {
          "position": 19,
          "driverNumber": 11,
          "driverId": "PER",
          "driver": "Sergio Perez",
          "team": "Cadillac",
          "startingGrid": null,
          "laps": 19,
          "time": "+28.241",
          "points": 0
        },
        {
          "position": 20,
          "driverNumber": 27,
          "driverId": "HUL",
          "driver": "Nico Hulkenberg",
          "team": "Sauber",
          "startingGrid": null,
          "laps": 12,
          "time": "DNF",
          "points": 0,
          "status": "DNF"
        },
        {
          "position": 21,
          "driverNumber": 77,
          "driverId": "BOT",
          "driver": "Valtteri Bottas",
          "team": "Cadillac",
          "startingGrid": null,
          "laps": 12,
          "time": "DNF",
          "points": 0,
          "status": "DNF"
        },
        {
          "position": 22,
          "driverNumber": 41,
          "driverId": "LIN",
          "driver": "Arvid Lindblad",
          "team": "Racing Bulls",
          "startingGrid": null,
          "laps": 11,
          "time": "DNF",
          "points": 0,
          "status": "DNF"
        }
      ]
    },
    {
      "round": 5,
      "qualifyingResults": [
        {
          "position": 1,
          "driverNumber": 12,
          "driverId": "ANT",
          "driver": "Kimi Antonelli",
          "team": "Mercedes",
          "q1": "1:32.064",
          "q2": null,
          "q3": null,
          "laps": 0
        },
        {
          "position": 2,
          "driverNumber": 63,
          "driverId": "RUS",
          "driver": "George Russell",
          "team": "Mercedes",
          "q1": "1:32.286",
          "q2": null,
          "q3": null,
          "laps": 0
        },
        {
          "position": 3,
          "driverNumber": 44,
          "driverId": "HAM",
          "driver": "Lewis Hamilton",
          "team": "Ferrari",
          "q1": "1:32.415",
          "q2": null,
          "q3": null,
          "laps": 0
        },
        {
          "position": 4,
          "driverNumber": 16,
          "driverId": "LEC",
          "driver": "Charles Leclerc",
          "team": "Ferrari",
          "q1": "1:32.428",
          "q2": null,
          "q3": null,
          "laps": 0
        },
        {
          "position": 5,
          "driverNumber": 81,
          "driverId": "PIA",
          "driver": "Oscar Piastri",
          "team": "McLaren",
          "q1": "1:32.550",
          "q2": null,
          "q3": null,
          "laps": 0
        },
        {
          "position": 6,
          "driverNumber": 1,
          "driverId": "NOR",
          "driver": "Lando Norris",
          "team": "McLaren",
          "q1": "1:32.608",
          "q2": null,
          "q3": null,
          "laps": 0
        },
        {
          "position": 7,
          "driverNumber": 10,
          "driverId": "GAS",
          "driver": "Pierre Gasly",
          "team": "Alpine",
          "q1": "1:32.873",
          "q2": null,
          "q3": null,
          "laps": 0
        },
        {
          "position": 8,
          "driverNumber": 3,
          "driverId": "VER",
          "driver": "Max Verstappen",
          "team": "Red Bull Racing",
          "q1": "1:33.002",
          "q2": null,
          "q3": null,
          "laps": 0
        },
        {
          "position": 9,
          "driverNumber": 6,
          "driverId": "HAD",
          "driver": "Isack Hadjar",
          "team": "Red Bull Racing",
          "q1": "1:33.121",
          "q2": null,
          "q3": null,
          "laps": 0
        },
        {
          "position": 10,
          "driverNumber": 87,
          "driverId": "BEA",
          "driver": "Oliver Bearman",
          "team": "Haas",
          "q1": "1:33.292",
          "q2": null,
          "q3": null,
          "laps": 0
        },
        {
          "position": 11,
          "driverNumber": 27,
          "driverId": "HUL",
          "driver": "Nico Hulkenberg",
          "team": "Sauber",
          "q1": "1:33.354",
          "q2": null,
          "q3": null,
          "laps": 0
        },
        {
          "position": 12,
          "driverNumber": 43,
          "driverId": "COL",
          "driver": "Franco Colapinto",
          "team": "Alpine",
          "q1": "1:33.357",
          "q2": null,
          "q3": null,
          "laps": 0
        },
        {
          "position": 13,
          "driverNumber": 31,
          "driverId": "OCO",
          "driver": "Esteban Ocon",
          "team": "Haas",
          "q1": "1:33.538",
          "q2": null,
          "q3": null,
          "laps": 0
        },
        {
          "position": 14,
          "driverNumber": 30,
          "driverId": "LAW",
          "driver": "Liam Lawson",
          "team": "Racing Bulls",
          "q1": "1:33.765",
          "q2": null,
          "q3": null,
          "laps": 0
        },
        {
          "position": 15,
          "driverNumber": 41,
          "driverId": "LIN",
          "driver": "Arvid Lindblad",
          "team": "Racing Bulls",
          "q1": "1:33.784",
          "q2": null,
          "q3": null,
          "laps": 0
        },
        {
          "position": 16,
          "driverNumber": 5,
          "driverId": "BOR",
          "driver": "Gabriel Bortoleto",
          "team": "Sauber",
          "q1": "1:33.965",
          "q2": null,
          "q3": null,
          "laps": 0
        },
        {
          "position": 17,
          "driverNumber": 55,
          "driverId": "SAI",
          "driver": "Carlos Sainz",
          "team": "Williams",
          "q1": "1:34.317",
          "q2": null,
          "q3": null,
          "laps": 0
        },
        {
          "position": 18,
          "driverNumber": 23,
          "driverId": "ALB",
          "driver": "Alexander Albon",
          "team": "Williams",
          "q1": "1:34.772",
          "q2": null,
          "q3": null,
          "laps": 0
        },
        {
          "position": 19,
          "driverNumber": 14,
          "driverId": "ALO",
          "driver": "Fernando Alonso",
          "team": "Aston Martin",
          "q1": "1:35.203",
          "q2": null,
          "q3": null,
          "laps": 0
        },
        {
          "position": 20,
          "driverNumber": 77,
          "driverId": "BOT",
          "driver": "Valtteri Bottas",
          "team": "Cadillac",
          "q1": "1:35.436",
          "q2": null,
          "q3": null,
          "laps": 0
        },
        {
          "position": 21,
          "driverNumber": 18,
          "driverId": "STR",
          "driver": "Lance Stroll",
          "team": "Aston Martin",
          "q1": "1:35.995",
          "q2": null,
          "q3": null,
          "laps": 0
        },
        {
          "position": 22,
          "driverNumber": 11,
          "driverId": "PER",
          "driver": "Sergio Perez",
          "team": "Cadillac",
          "q1": "1:36.906",
          "q2": null,
          "q3": null,
          "laps": 0
        }
      ]
    },
    {
      "round": 6,
      "raceResults": [
        {
          "position": 1,
          "driverNumber": 12,
          "driverId": "ANT",
          "driver": "Kimi Antonelli",
          "team": "Mercedes",
          "startingGrid": 1,
          "laps": 56,
          "time": "1:33:15.607",
          "points": 25
        },
        {
          "position": 2,
          "driverNumber": 63,
          "driverId": "RUS",
          "driver": "George Russell",
          "team": "Mercedes",
          "startingGrid": 2,
          "laps": 56,
          "time": "+5.515",
          "points": 18
        },
        {
          "position": 3,
          "driverNumber": 44,
          "driverId": "HAM",
          "driver": "Lewis Hamilton",
          "team": "Ferrari",
          "startingGrid": 3,
          "laps": 56,
          "time": "+25.267",
          "points": 15
        },
        {
          "position": 4,
          "driverNumber": 16,
          "driverId": "LEC",
          "driver": "Charles Leclerc",
          "team": "Ferrari",
          "startingGrid": 4,
          "laps": 56,
          "time": "+28.894",
          "points": 12
        },
        {
          "position": 5,
          "driverNumber": 87,
          "driverId": "BEA",
          "driver": "Oliver Bearman",
          "team": "Haas",
          "startingGrid": 10,
          "laps": 56,
          "time": "+57.268",
          "points": 10
        },
        {
          "position": 6,
          "driverNumber": 10,
          "driverId": "GAS",
          "driver": "Pierre Gasly",
          "team": "Alpine",
          "startingGrid": 7,
          "laps": 56,
          "time": "+59.647",
          "points": 8
        },
        {
          "position": 7,
          "driverNumber": 30,
          "driverId": "LAW",
          "driver": "Liam Lawson",
          "team": "Racing Bulls",
          "startingGrid": 14,
          "laps": 56,
          "time": "+1:20.588",
          "points": 6
        },
        {
          "position": 8,
          "driverNumber": 6,
          "driverId": "HAD",
          "driver": "Isack Hadjar",
          "team": "Red Bull Racing",
          "startingGrid": 9,
          "laps": 56,
          "time": "+1:27.247",
          "points": 4
        },
        {
          "position": 9,
          "driverNumber": 55,
          "driverId": "SAI",
          "driver": "Carlos Sainz Jr.",
          "team": "Williams",
          "startingGrid": 17,
          "laps": 55,
          "time": "+1 lap",
          "points": 2
        },
        {
          "position": 10,
          "driverNumber": 43,
          "driverId": "COL",
          "driver": "Franco Colapinto",
          "team": "Alpine",
          "startingGrid": 12,
          "laps": 55,
          "time": "+1 lap",
          "points": 1
        },
        {
          "position": 11,
          "driverNumber": 27,
          "driverId": "HUL",
          "driver": "Nico Hulkenberg",
          "team": "Sauber",
          "startingGrid": 11,
          "laps": 55,
          "time": "+1 lap",
          "points": 0
        },
        {
          "position": 12,
          "driverNumber": 41,
          "driverId": "LIN",
          "driver": "Arvid Lindblad",
          "team": "Racing Bulls",
          "startingGrid": 15,
          "laps": 55,
          "time": "+1 lap",
          "points": 0
        },
        {
          "position": 13,
          "driverNumber": 77,
          "driverId": "BOT",
          "driver": "Valtteri Bottas",
          "team": "Cadillac",
          "startingGrid": 20,
          "laps": 55,
          "time": "+1 lap",
          "points": 0
        },
        {
          "position": 14,
          "driverNumber": 31,
          "driverId": "OCO",
          "driver": "Esteban Ocon",
          "team": "Haas",
          "startingGrid": 13,
          "laps": 55,
          "time": "+1 lap",
          "points": 0
        },
        {
          "position": 15,
          "driverNumber": 11,
          "driverId": "PER",
          "driver": "Sergio Perez",
          "team": "Cadillac",
          "startingGrid": 22,
          "laps": 55,
          "time": "+1 lap",
          "points": 0
        },
        {
          "position": 16,
          "driverNumber": 3,
          "driverId": "VER",
          "driver": "Max Verstappen",
          "team": "Red Bull Racing",
          "startingGrid": 8,
          "laps": 42,
          "time": "DNF",
          "points": 0,
          "status": "DNF"
        },
        {
          "position": 17,
          "driverNumber": 14,
          "driverId": "ALO",
          "driver": "Fernando Alonso",
          "team": "Aston Martin",
          "startingGrid": 19,
          "laps": 38,
          "time": "DNF",
          "points": 0,
          "status": "DNF"
        },
        {
          "position": 18,
          "driverNumber": 18,
          "driverId": "STR",
          "driver": "Lance Stroll",
          "team": "Aston Martin",
          "startingGrid": 21,
          "laps": 25,
          "time": "DNF",
          "points": 0,
          "status": "DNF"
        },
        {
          "position": 19,
          "driverNumber": 1,
          "driverId": "NOR",
          "driver": "Lando Norris",
          "team": "McLaren",
          "startingGrid": 6,
          "laps": 0,
          "time": "DNS",
          "points": 0,
          "status": "DNS"
        },
        {
          "position": 20,
          "driverNumber": 81,
          "driverId": "PIA",
          "driver": "Oscar Piastri",
          "team": "McLaren",
          "startingGrid": 5,
          "laps": 0,
          "time": "DNS",
          "points": 0,
          "status": "DNS"
        },
        {
          "position": 21,
          "driverNumber": 5,
          "driverId": "BOR",
          "driver": "Gabriel Bortoleto",
          "team": "Sauber",
          "startingGrid": 16,
          "laps": 0,
          "time": "DNS",
          "points": 0,
          "status": "DNS"
        },
        {
          "position": 22,
          "driverNumber": 23,
          "driverId": "ALB",
          "driver": "Alexander Albon",
          "team": "Williams",
          "startingGrid": 18,
          "laps": 0,
          "time": "DNS",
          "points": 0,
          "status": "DNS"
        }
      ]
    },
    {
      "round": 7,
      "qualifyingResults": [
        {
          "position": 1,
          "driverNumber": 12,
          "driverId": "ANT",
          "driver": "Kimi Antonelli",
          "team": "Mercedes",
          "q1": "1:30.035",
          "q2": "1:29.048",
          "q3": "1:28.778",
          "laps": 15
        },
        {
          "position": 2,
          "driverNumber": 63,
          "driverId": "RUS",
          "driver": "George Russell",
          "team": "Mercedes",
          "q1": "1:29.967",
          "q2": "1:29.686",
          "q3": "1:29.076",
          "laps": 21
        },
        {
          "position": 3,
          "driverNumber": 81,
          "driverId": "PIA",
          "driver": "Oscar Piastri",
          "team": "McLaren",
          "q1": "1:30.200",
          "q2": "1:29.451",
          "q3": "1:29.132",
          "laps": 20
        },
        {
          "position": 4,
          "driverNumber": 16,
          "driverId": "LEC",
          "driver": "Charles Leclerc",
          "team": "Ferrari",
          "q1": "1:29.915",
          "q2": "1:29.303",
          "q3": "1:29.405",
          "laps": 18
        },
        {
          "position": 5,
          "driverNumber": 1,
          "driverId": "NOR",
          "driver": "Lando Norris",
          "team": "McLaren",
          "q1": "1:30.401",
          "q2": "1:29.795",
          "q3": "1:29.409",
          "laps": 20
        },
        {
          "position": 6,
          "driverNumber": 44,
          "driverId": "HAM",
          "driver": "Lewis Hamilton",
          "team": "Ferrari",
          "q1": "1:30.309",
          "q2": "1:29.589",
          "q3": "1:29.567",
          "laps": 20
        },
        {
          "position": 7,
          "driverNumber": 10,
          "driverId": "GAS",
          "driver": "Pierre Gasly",
          "team": "Alpine",
          "q1": "1:30.584",
          "q2": "1:29.874",
          "q3": "1:29.691",
          "laps": 18
        },
        {
          "position": 8,
          "driverNumber": 6,
          "driverId": "HAD",
          "driver": "Isack Hadjar",
          "team": "Red Bull Racing",
          "q1": "1:30.662",
          "q2": "1:30.104",
          "q3": "1:29.978",
          "laps": 17
        },
        {
          "position": 9,
          "driverNumber": 5,
          "driverId": "BOR",
          "driver": "Gabriel Bortoleto",
          "team": "Sauber",
          "q1": "1:30.359",
          "q2": "1:29.990",
          "q3": "1:30.274",
          "laps": 20
        },
        {
          "position": 10,
          "driverNumber": 41,
          "driverId": "LIN",
          "driver": "Arvid Lindblad",
          "team": "Racing Bulls",
          "q1": "1:30.781",
          "q2": "1:30.109",
          "q3": "1:30.319",
          "laps": 21
        },
        {
          "position": 11,
          "driverNumber": 3,
          "driverId": "VER",
          "driver": "Max Verstappen",
          "team": "Red Bull Racing",
          "q1": "1:30.519",
          "q2": "1:30.262",
          "q3": null,
          "laps": 12
        },
        {
          "position": 12,
          "driverNumber": 31,
          "driverId": "OCO",
          "driver": "Esteban Ocon",
          "team": "Haas",
          "q1": "1:30.915",
          "q2": "1:30.309",
          "q3": null,
          "laps": 15
        },
        {
          "position": 13,
          "driverNumber": 27,
          "driverId": "HUL",
          "driver": "Nico Hulkenberg",
          "team": "Sauber",
          "q1": "1:30.358",
          "q2": "1:30.387",
          "q3": null,
          "laps": 14
        },
        {
          "position": 14,
          "driverNumber": 30,
          "driverId": "LAW",
          "driver": "Liam Lawson",
          "team": "Racing Bulls",
          "q1": "1:30.657",
          "q2": "1:30.495",
          "q3": null,
          "laps": 15
        },
        {
          "position": 15,
          "driverNumber": 43,
          "driverId": "COL",
          "driver": "Franco Colapinto",
          "team": "Alpine",
          "q1": "1:30.931",
          "q2": "1:30.627",
          "q3": null,
          "laps": 12
        },
        {
          "position": 16,
          "driverNumber": 55,
          "driverId": "SAI",
          "driver": "Carlos Sainz",
          "team": "Williams",
          "q1": "1:30.927",
          "q2": "1:31.033",
          "q3": null,
          "laps": 15
        },
        {
          "position": 17,
          "driverNumber": 23,
          "driverId": "ALB",
          "driver": "Alexander Albon",
          "team": "Williams",
          "q1": "1:31.088",
          "q2": null,
          "q3": null,
          "laps": 9
        },
        {
          "position": 18,
          "driverNumber": 87,
          "driverId": "BEA",
          "driver": "Oliver Bearman",
          "team": "Haas",
          "q1": "1:31.090",
          "q2": null,
          "q3": null,
          "laps": 9
        },
        {
          "position": 19,
          "driverNumber": 11,
          "driverId": "PER",
          "driver": "Sergio Perez",
          "team": "Cadillac",
          "q1": "1:32.206",
          "q2": null,
          "q3": null,
          "laps": 6
        },
        {
          "position": 20,
          "driverNumber": 77,
          "driverId": "BOT",
          "driver": "Valtteri Bottas",
          "team": "Cadillac",
          "q1": "1:32.330",
          "q2": null,
          "q3": null,
          "laps": 9
        },
        {
          "position": 21,
          "driverNumber": 14,
          "driverId": "ALO",
          "driver": "Fernando Alonso",
          "team": "Aston Martin",
          "q1": "1:32.646",
          "q2": null,
          "q3": null,
          "laps": 9
        },
        {
          "position": 22,
          "driverNumber": 18,
          "driverId": "STR",
          "driver": "Lance Stroll",
          "team": "Aston Martin",
          "q1": "1:32.920",
          "q2": null,
          "q3": null,
          "laps": 9
        }
      ]
    },
    {
      "round": 8,
      "raceResults": [
        {
          "position": 1,
          "driverNumber": 12,
          "driverId": "ANT",
          "driver": "Kimi Antonelli",
          "team": "Mercedes",
          "startingGrid": null,
          "laps": 53,
          "time": "1:28:03.403",
          "points": 25,
          "setFastestLap": false
        },
        {
          "position": 2,
          "driverNumber": 81,
          "driverId": "PIA",
          "driver": "Oscar Piastri",
          "team": "McLaren",
          "startingGrid": null,
          "laps": 53,
          "time": "+13.722s",
          "points": 18,
          "setFastestLap": false
        },
        {
          "position": 3,
          "driverNumber": 16,
          "driverId": "LEC",
          "driver": "Charles Leclerc",
          "team": "Ferrari",
          "startingGrid": null,
          "laps": 53,
          "time": "+15.270s",
          "points": 15,
          "setFastestLap": false
        },
        {
          "position": 4,
          "driverNumber": 63,
          "driverId": "RUS",
          "driver": "George Russell",
          "team": "Mercedes",
          "startingGrid": null,
          "laps": 53,
          "time": "+15.754s",
          "points": 12,
          "setFastestLap": false
        },
        {
          "position": 5,
          "driverNumber": 1,
          "driverId": "NOR",
          "driver": "Lando Norris",
          "team": "McLaren",
          "startingGrid": null,
          "laps": 53,
          "time": "+23.479s",
          "points": 10,
          "setFastestLap": false
        },
        {
          "position": 6,
          "driverNumber": 44,
          "driverId": "HAM",
          "driver": "Lewis Hamilton",
          "team": "Ferrari",
          "startingGrid": null,
          "laps": 53,
          "time": "+25.037s",
          "points": 8,
          "setFastestLap": false
        },
        {
          "position": 7,
          "driverNumber": 10,
          "driverId": "GAS",
          "driver": "Pierre Gasly",
          "team": "Alpine",
          "startingGrid": null,
          "laps": 53,
          "time": "+32.340s",
          "points": 6,
          "setFastestLap": false
        },
        {
          "position": 8,
          "driverNumber": 3,
          "driverId": "VER",
          "driver": "Max Verstappen",
          "team": "Red Bull Racing",
          "startingGrid": null,
          "laps": 53,
          "time": "+32.677s",
          "points": 4,
          "setFastestLap": false
        },
        {
          "position": 9,
          "driverNumber": 30,
          "driverId": "LAW",
          "driver": "Liam Lawson",
          "team": "Racing Bulls",
          "startingGrid": null,
          "laps": 53,
          "time": "+50.180s",
          "points": 2,
          "setFastestLap": false
        },
        {
          "position": 10,
          "driverNumber": 31,
          "driverId": "OCO",
          "driver": "Esteban Ocon",
          "team": "Haas",
          "startingGrid": null,
          "laps": 53,
          "time": "+51.216s",
          "points": 1,
          "setFastestLap": false
        },
        {
          "position": 11,
          "driverNumber": 27,
          "driverId": "HUL",
          "driver": "Nico Hulkenberg",
          "team": "Sauber",
          "startingGrid": null,
          "laps": 53,
          "time": "+52.280s",
          "points": 0,
          "setFastestLap": false
        },
        {
          "position": 12,
          "driverNumber": 6,
          "driverId": "HAD",
          "driver": "Isack Hadjar",
          "team": "Red Bull Racing",
          "startingGrid": null,
          "laps": 53,
          "time": "+56.154s",
          "points": 0,
          "setFastestLap": false
        },
        {
          "position": 13,
          "driverNumber": 5,
          "driverId": "BOR",
          "driver": "Gabriel Bortoleto",
          "team": "Sauber",
          "startingGrid": null,
          "laps": 53,
          "time": "+59.078s",
          "points": 0,
          "setFastestLap": false
        },
        {
          "position": 14,
          "driverNumber": 41,
          "driverId": "LIN",
          "driver": "Arvid Lindblad",
          "team": "Racing Bulls",
          "startingGrid": null,
          "laps": 53,
          "time": "+59.848s",
          "points": 0,
          "setFastestLap": false
        },
        {
          "position": 15,
          "driverNumber": 55,
          "driverId": "SAI",
          "driver": "Carlos Sainz",
          "team": "Williams",
          "startingGrid": null,
          "laps": 53,
          "time": "+65.008s",
          "points": 0,
          "setFastestLap": false
        },
        {
          "position": 16,
          "driverNumber": 43,
          "driverId": "COL",
          "driver": "Franco Colapinto",
          "team": "Alpine",
          "startingGrid": null,
          "laps": 53,
          "time": "+65.773s",
          "points": 0,
          "setFastestLap": false
        },
        {
          "position": 17,
          "driverNumber": 11,
          "driverId": "PER",
          "driver": "Sergio Perez",
          "team": "Cadillac",
          "startingGrid": null,
          "laps": 53,
          "time": "+92.453s",
          "points": 0,
          "setFastestLap": false
        },
        {
          "position": 18,
          "driverNumber": 14,
          "driverId": "ALO",
          "driver": "Fernando Alonso",
          "team": "Aston Martin",
          "startingGrid": null,
          "laps": 52,
          "time": "+1 lap",
          "points": 0,
          "setFastestLap": false
        },
        {
          "position": 19,
          "driverNumber": 77,
          "driverId": "BOT",
          "driver": "Valtteri Bottas",
          "team": "Cadillac",
          "startingGrid": null,
          "laps": 52,
          "time": "+1 lap",
          "points": 0,
          "setFastestLap": false
        },
        {
          "position": 20,
          "driverNumber": 23,
          "driverId": "ALB",
          "driver": "Alexander Albon",
          "team": "Williams",
          "startingGrid": null,
          "laps": 51,
          "time": "+2 laps",
          "points": 0,
          "setFastestLap": false
        },
        {
          "position": 21,
          "driverNumber": 18,
          "driverId": "STR",
          "driver": "Lance Stroll",
          "team": "Aston Martin",
          "startingGrid": null,
          "laps": 30,
          "time": "DNF",
          "points": 0,
          "setFastestLap": false,
          "status": "DNF"
        },
        {
          "position": 22,
          "driverNumber": 87,
          "driverId": "BEA",
          "driver": "Oliver Bearman",
          "team": "Haas",
          "startingGrid": null,
          "laps": 20,
          "time": "DNF",
          "points": 0,
          "setFastestLap": false,
          "status": "DNF"
        }
      ]
    }
  ],
  "drivers": [
    {
      "id": "RUS",
      "name": "George Russell",
      "number": 63,
      "team": "Mercedes",
      "teamId": "mercedes",
      "teamColor": "#27F4D2",
      "results": [
        {
          "round": 1,
          "position": 1,
          "points": 0,
          "cumulativePoints": 0
        },
        {
          "round": 2,
          "position": 1,
          "points": 25,
          "grid": 1,
          "fastestLapTime": "1:22.670",
          "cumulativePoints": 25
        },
        {
          "round": 3,
          "position": 1,
          "points": 0,
          "cumulativePoints": 25
        },
        {
          "round": 4,
          "position": 1,
          "points": 8,
          "cumulativePoints": 33
        },
        {
          "round": 5,
          "position": 2,
          "points": 0,
          "cumulativePoints": 33
        },
        {
          "round": 6,
          "position": 2,
          "points": 18,
          "grid": 2,
          "cumulativePoints": 51
        },
        {
          "round": 7,
          "position": 2,
          "points": 0,
          "cumulativePoints": 51
        },
        {
          "round": 8,
          "position": 4,
          "points": 12,
          "cumulativePoints": 63,
          "grid": null
        }
      ],
      "photo": "/drivers/rus.png"
    },
    {
      "id": "ANT",
      "name": "Kimi Antonelli",
      "number": 12,
      "team": "Mercedes",
      "teamId": "mercedes",
      "teamColor": "#27F4D2",
      "results": [
        {
          "round": 1,
          "position": 2,
          "points": 0,
          "cumulativePoints": 0
        },
        {
          "round": 2,
          "position": 2,
          "points": 18,
          "grid": 2,
          "fastestLapTime": "1:22.417",
          "cumulativePoints": 18
        },
        {
          "round": 3,
          "position": 2,
          "points": 0,
          "cumulativePoints": 18
        },
        {
          "round": 4,
          "position": 5,
          "points": 4,
          "cumulativePoints": 22
        },
        {
          "round": 5,
          "position": 1,
          "points": 0,
          "cumulativePoints": 22
        },
        {
          "round": 6,
          "position": 1,
          "points": 25,
          "grid": 1,
          "cumulativePoints": 47
        },
        {
          "round": 7,
          "position": 1,
          "points": 0,
          "cumulativePoints": 47
        },
        {
          "round": 8,
          "position": 1,
          "points": 25,
          "cumulativePoints": 72,
          "grid": null
        }
      ],
      "photo": "/drivers/ant.png"
    },
    {
      "id": "LEC",
      "name": "Charles Leclerc",
      "number": 16,
      "team": "Ferrari",
      "teamId": "ferrari",
      "teamColor": "#E8002D",
      "results": [
        {
          "round": 1,
          "position": 4,
          "points": 0,
          "cumulativePoints": 0
        },
        {
          "round": 2,
          "position": 3,
          "points": 15,
          "grid": 4,
          "fastestLapTime": "1:22.579",
          "cumulativePoints": 15
        },
        {
          "round": 3,
          "position": 6,
          "points": 0,
          "cumulativePoints": 15
        },
        {
          "round": 4,
          "position": 2,
          "points": 7,
          "cumulativePoints": 22
        },
        {
          "round": 5,
          "position": 4,
          "points": 0,
          "cumulativePoints": 22
        },
        {
          "round": 6,
          "position": 4,
          "points": 12,
          "grid": 4,
          "cumulativePoints": 34
        },
        {
          "round": 7,
          "position": 4,
          "points": 0,
          "cumulativePoints": 34
        },
        {
          "round": 8,
          "position": 3,
          "points": 15,
          "cumulativePoints": 49,
          "grid": null
        }
      ],
      "photo": "/drivers/lec.png"
    },
    {
      "id": "HAM",
      "name": "Lewis Hamilton",
      "number": 44,
      "team": "Ferrari",
      "teamId": "ferrari",
      "teamColor": "#E8002D",
      "results": [
        {
          "round": 1,
          "position": 7,
          "points": 0,
          "cumulativePoints": 0
        },
        {
          "round": 2,
          "position": 4,
          "points": 12,
          "grid": 7,
          "fastestLapTime": "1:22.423",
          "cumulativePoints": 12
        },
        {
          "round": 3,
          "position": 4,
          "points": 0,
          "cumulativePoints": 12
        },
        {
          "round": 4,
          "position": 3,
          "points": 6,
          "cumulativePoints": 18
        },
        {
          "round": 5,
          "position": 3,
          "points": 0,
          "cumulativePoints": 18
        },
        {
          "round": 6,
          "position": 3,
          "points": 15,
          "grid": 3,
          "cumulativePoints": 33
        },
        {
          "round": 7,
          "position": 6,
          "points": 0,
          "cumulativePoints": 33
        },
        {
          "round": 8,
          "position": 6,
          "points": 8,
          "cumulativePoints": 41,
          "grid": null
        }
      ],
      "photo": "/drivers/ham.png"
    },
    {
      "id": "NOR",
      "name": "Lando Norris",
      "number": 1,
      "team": "McLaren",
      "teamId": "mclaren",
      "teamColor": "#FF8000",
      "results": [
        {
          "round": 1,
          "position": 6,
          "points": 0,
          "cumulativePoints": 0
        },
        {
          "round": 2,
          "position": 5,
          "points": 10,
          "grid": 6,
          "fastestLapTime": "1:22.358",
          "cumulativePoints": 10
        },
        {
          "round": 3,
          "position": 3,
          "points": 0,
          "cumulativePoints": 10
        },
        {
          "round": 4,
          "position": 4,
          "points": 5,
          "cumulativePoints": 15
        },
        {
          "round": 5,
          "position": 6,
          "points": 0,
          "cumulativePoints": 15
        },
        {
          "round": 6,
          "position": 19,
          "points": 0,
          "grid": 6,
          "status": "DNS",
          "cumulativePoints": 15
        },
        {
          "round": 7,
          "position": 5,
          "points": 0,
          "cumulativePoints": 15
        },
        {
          "round": 8,
          "position": 5,
          "points": 10,
          "cumulativePoints": 25,
          "grid": null
        }
      ],
      "photo": "/drivers/nor.png"
    },
    {
      "id": "VER",
      "name": "Max Verstappen",
      "number": 3,
      "team": "Red Bull Racing",
      "teamId": "red-bull",
      "teamColor": "#3671C6",
      "results": [
        {
          "round": 1,
          "position": 20,
          "points": 0,
          "cumulativePoints": 0
        },
        {
          "round": 2,
          "position": 6,
          "points": 8,
          "grid": 20,
          "fastestLapTime": "1:22.091",
          "setFastestLap": true,
          "cumulativePoints": 8
        },
        {
          "round": 3,
          "position": 8,
          "points": 0,
          "cumulativePoints": 8
        },
        {
          "round": 4,
          "position": 9,
          "points": 0,
          "cumulativePoints": 8
        },
        {
          "round": 5,
          "position": 8,
          "points": 0,
          "cumulativePoints": 8
        },
        {
          "round": 6,
          "position": 16,
          "points": 0,
          "grid": 8,
          "status": "DNF",
          "cumulativePoints": 8
        },
        {
          "round": 7,
          "position": 11,
          "points": 0,
          "cumulativePoints": 8
        },
        {
          "round": 8,
          "position": 8,
          "points": 4,
          "cumulativePoints": 12,
          "grid": null
        }
      ],
      "photo": "/drivers/ver.png"
    },
    {
      "id": "BEA",
      "name": "Oliver Bearman",
      "number": 87,
      "team": "Haas",
      "teamId": "haas",
      "teamColor": "#B6BABD",
      "results": [
        {
          "round": 1,
          "position": 12,
          "points": 0,
          "cumulativePoints": 0
        },
        {
          "round": 2,
          "position": 7,
          "points": 6,
          "grid": 12,
          "fastestLapTime": "1:24.020",
          "cumulativePoints": 6
        },
        {
          "round": 3,
          "position": 9,
          "points": 0,
          "cumulativePoints": 6
        },
        {
          "round": 4,
          "position": 8,
          "points": 1,
          "cumulativePoints": 7
        },
        {
          "round": 5,
          "position": 10,
          "points": 0,
          "cumulativePoints": 7
        },
        {
          "round": 6,
          "position": 5,
          "points": 10,
          "grid": 10,
          "cumulativePoints": 17
        },
        {
          "round": 7,
          "position": 18,
          "points": 0,
          "cumulativePoints": 17
        },
        {
          "round": 8,
          "position": 22,
          "points": 0,
          "cumulativePoints": 17,
          "grid": null,
          "status": "DNF"
        }
      ],
      "photo": "/drivers/bea.png"
    },
    {
      "id": "LIN",
      "name": "Arvid Lindblad",
      "number": 41,
      "team": "Racing Bulls",
      "teamId": "racing-bulls",
      "teamColor": "#6692FF",
      "results": [
        {
          "round": 1,
          "position": 9,
          "points": 0,
          "cumulativePoints": 0
        },
        {
          "round": 2,
          "position": 8,
          "points": 4,
          "grid": 9,
          "fastestLapTime": "1:24.182",
          "cumulativePoints": 4
        },
        {
          "round": 3,
          "position": 15,
          "points": 0,
          "cumulativePoints": 4
        },
        {
          "round": 4,
          "position": 22,
          "points": 0,
          "cumulativePoints": 4,
          "status": "DNF"
        },
        {
          "round": 5,
          "position": 15,
          "points": 0,
          "cumulativePoints": 4
        },
        {
          "round": 6,
          "position": 12,
          "points": 0,
          "grid": 15,
          "cumulativePoints": 4
        },
        {
          "round": 7,
          "position": 10,
          "points": 0,
          "cumulativePoints": 4
        },
        {
          "round": 8,
          "position": 14,
          "points": 0,
          "cumulativePoints": 4,
          "grid": null
        }
      ],
      "photo": "/drivers/lin.png"
    },
    {
      "id": "PIA",
      "name": "Oscar Piastri",
      "number": 81,
      "team": "McLaren",
      "teamId": "mclaren",
      "teamColor": "#FF8000",
      "results": [
        {
          "round": 1,
          "position": 5,
          "points": 0,
          "cumulativePoints": 0
        },
        {
          "round": 2,
          "position": 21,
          "points": 0,
          "grid": 5,
          "status": "DNS",
          "cumulativePoints": 0
        },
        {
          "round": 3,
          "position": 5,
          "points": 0,
          "cumulativePoints": 0
        },
        {
          "round": 4,
          "position": 6,
          "points": 3,
          "cumulativePoints": 3
        },
        {
          "round": 5,
          "position": 5,
          "points": 0,
          "cumulativePoints": 3
        },
        {
          "round": 6,
          "position": 20,
          "points": 0,
          "grid": 5,
          "status": "DNS",
          "cumulativePoints": 3
        },
        {
          "round": 7,
          "position": 3,
          "points": 0,
          "cumulativePoints": 3
        },
        {
          "round": 8,
          "position": 2,
          "points": 18,
          "cumulativePoints": 21,
          "grid": null
        }
      ],
      "photo": "/drivers/pia.png"
    },
    {
      "id": "BOR",
      "name": "Gabriel Bortoleto",
      "number": 5,
      "team": "Audi",
      "teamId": "sauber",
      "teamColor": "#52E252",
      "results": [
        {
          "round": 1,
          "position": 10,
          "points": 0,
          "cumulativePoints": 0
        },
        {
          "round": 2,
          "position": 9,
          "points": 2,
          "grid": 10,
          "fastestLapTime": "1:23.257",
          "cumulativePoints": 2
        },
        {
          "round": 3,
          "position": 14,
          "points": 0,
          "cumulativePoints": 2
        },
        {
          "round": 4,
          "position": 13,
          "points": 0,
          "cumulativePoints": 2
        },
        {
          "round": 5,
          "position": 16,
          "points": 0,
          "cumulativePoints": 2
        },
        {
          "round": 6,
          "position": 21,
          "points": 0,
          "grid": 16,
          "status": "DNS",
          "cumulativePoints": 2
        },
        {
          "round": 7,
          "position": 9,
          "points": 0,
          "cumulativePoints": 2
        },
        {
          "round": 8,
          "position": 13,
          "points": 0,
          "cumulativePoints": 2,
          "grid": null
        }
      ],
      "photo": "/drivers/bor.png"
    },
    {
      "id": "LAW",
      "name": "Liam Lawson",
      "number": 30,
      "team": "Racing Bulls",
      "teamId": "racing-bulls",
      "teamColor": "#6692FF",
      "results": [
        {
          "round": 1,
          "position": 8,
          "points": 0,
          "cumulativePoints": 0
        },
        {
          "round": 2,
          "position": 13,
          "points": 0,
          "grid": 8,
          "fastestLapTime": "1:23.783",
          "cumulativePoints": 0
        },
        {
          "round": 3,
          "position": 13,
          "points": 0,
          "cumulativePoints": 0
        },
        {
          "round": 4,
          "position": 7,
          "points": 2,
          "cumulativePoints": 2
        },
        {
          "round": 5,
          "position": 14,
          "points": 0,
          "cumulativePoints": 2
        },
        {
          "round": 6,
          "position": 7,
          "points": 6,
          "grid": 14,
          "cumulativePoints": 8
        },
        {
          "round": 7,
          "position": 14,
          "points": 0,
          "cumulativePoints": 8
        },
        {
          "round": 8,
          "position": 9,
          "points": 2,
          "cumulativePoints": 10,
          "grid": null
        }
      ],
      "photo": "/drivers/law.png"
    },
    {
      "id": "GAS",
      "name": "Pierre Gasly",
      "number": 10,
      "team": "Alpine",
      "teamId": "alpine",
      "teamColor": "#FF87BC",
      "results": [
        {
          "round": 1,
          "position": 14,
          "points": 0,
          "cumulativePoints": 0
        },
        {
          "round": 2,
          "position": 10,
          "points": 1,
          "grid": 14,
          "fastestLapTime": "1:24.486",
          "cumulativePoints": 1
        },
        {
          "round": 3,
          "position": 7,
          "points": 0,
          "cumulativePoints": 1
        },
        {
          "round": 4,
          "position": 11,
          "points": 0,
          "cumulativePoints": 1
        },
        {
          "round": 5,
          "position": 7,
          "points": 0,
          "cumulativePoints": 1
        },
        {
          "round": 6,
          "position": 6,
          "points": 8,
          "grid": 7,
          "cumulativePoints": 9
        },
        {
          "round": 7,
          "position": 7,
          "points": 0,
          "cumulativePoints": 9
        },
        {
          "round": 8,
          "position": 7,
          "points": 6,
          "cumulativePoints": 15,
          "grid": null
        }
      ],
      "photo": "/drivers/gas.png"
    },
    {
      "id": "OCO",
      "name": "Esteban Ocon",
      "number": 31,
      "team": "Haas",
      "teamId": "haas",
      "teamColor": "#B6BABD",
      "results": [
        {
          "round": 1,
          "position": 13,
          "points": 0,
          "cumulativePoints": 0
        },
        {
          "round": 2,
          "position": 11,
          "points": 0,
          "grid": 13,
          "fastestLapTime": "1:24.424",
          "cumulativePoints": 0
        },
        {
          "round": 3,
          "position": 12,
          "points": 0,
          "cumulativePoints": 0
        },
        {
          "round": 4,
          "position": 10,
          "points": 0,
          "cumulativePoints": 0
        },
        {
          "round": 5,
          "position": 13,
          "points": 0,
          "cumulativePoints": 0
        },
        {
          "round": 6,
          "position": 14,
          "points": 0,
          "grid": 13,
          "cumulativePoints": 0
        },
        {
          "round": 7,
          "position": 12,
          "points": 0,
          "cumulativePoints": 0
        },
        {
          "round": 8,
          "position": 10,
          "points": 1,
          "cumulativePoints": 1,
          "grid": null
        }
      ],
      "photo": "/drivers/oco.png"
    },
    {
      "id": "ALB",
      "name": "Alexander Albon",
      "number": 23,
      "team": "Williams",
      "teamId": "williams",
      "teamColor": "#1868DB",
      "results": [
        {
          "round": 1,
          "position": 15,
          "points": 0,
          "cumulativePoints": 0
        },
        {
          "round": 2,
          "position": 12,
          "points": 0,
          "grid": 15,
          "fastestLapTime": "1:24.375",
          "cumulativePoints": 0
        },
        {
          "round": 3,
          "position": 22,
          "points": 0,
          "cumulativePoints": 0
        },
        {
          "round": 4,
          "position": 16,
          "points": 0,
          "cumulativePoints": 0
        },
        {
          "round": 5,
          "position": 18,
          "points": 0,
          "cumulativePoints": 0
        },
        {
          "round": 6,
          "position": 22,
          "points": 0,
          "grid": 18,
          "status": "DNS",
          "cumulativePoints": 0
        },
        {
          "round": 7,
          "position": 17,
          "points": 0,
          "cumulativePoints": 0
        },
        {
          "round": 8,
          "position": 20,
          "points": 0,
          "cumulativePoints": 0,
          "grid": null
        }
      ],
      "photo": "/drivers/alb.png"
    },
    {
      "id": "COL",
      "name": "Franco Colapinto",
      "number": 43,
      "team": "Alpine",
      "teamId": "alpine",
      "teamColor": "#FF87BC",
      "results": [
        {
          "round": 1,
          "position": 16,
          "points": 0,
          "cumulativePoints": 0
        },
        {
          "round": 2,
          "position": 14,
          "points": 0,
          "grid": 16,
          "fastestLapTime": "1:22.926",
          "cumulativePoints": 0
        },
        {
          "round": 3,
          "position": 16,
          "points": 0,
          "cumulativePoints": 0
        },
        {
          "round": 4,
          "position": 14,
          "points": 0,
          "cumulativePoints": 0
        },
        {
          "round": 5,
          "position": 12,
          "points": 0,
          "cumulativePoints": 0
        },
        {
          "round": 6,
          "position": 10,
          "points": 1,
          "grid": 12,
          "cumulativePoints": 1
        },
        {
          "round": 7,
          "position": 15,
          "points": 0,
          "cumulativePoints": 1
        },
        {
          "round": 8,
          "position": 16,
          "points": 0,
          "cumulativePoints": 1,
          "grid": null
        }
      ],
      "photo": "/drivers/col.png"
    },
    {
      "id": "SAI",
      "name": "Carlos Sainz",
      "number": 55,
      "team": "Williams",
      "teamId": "williams",
      "teamColor": "#1868DB",
      "results": [
        {
          "round": 1,
          "position": 21,
          "points": 0,
          "cumulativePoints": 0
        },
        {
          "round": 2,
          "position": 15,
          "points": 0,
          "grid": 21,
          "fastestLapTime": "1:23.590",
          "cumulativePoints": 0
        },
        {
          "round": 3,
          "position": 17,
          "points": 0,
          "cumulativePoints": 0
        },
        {
          "round": 4,
          "position": 12,
          "points": 0,
          "cumulativePoints": 0
        },
        {
          "round": 5,
          "position": 17,
          "points": 0,
          "cumulativePoints": 0
        },
        {
          "round": 6,
          "position": 9,
          "points": 2,
          "grid": 17,
          "cumulativePoints": 2
        },
        {
          "round": 7,
          "position": 16,
          "points": 0,
          "cumulativePoints": 2
        },
        {
          "round": 8,
          "position": 15,
          "points": 0,
          "cumulativePoints": 2,
          "grid": null
        }
      ],
      "photo": "/drivers/sai.png"
    },
    {
      "id": "PER",
      "name": "Sergio Perez",
      "number": 11,
      "team": "Cadillac",
      "teamId": "cadillac",
      "teamColor": "#1D1D1B",
      "results": [
        {
          "round": 1,
          "position": 18,
          "points": 0,
          "cumulativePoints": 0
        },
        {
          "round": 2,
          "position": 16,
          "points": 0,
          "grid": 18,
          "fastestLapTime": "1:26.070",
          "cumulativePoints": 0
        },
        {
          "round": 3,
          "position": 21,
          "points": 0,
          "cumulativePoints": 0
        },
        {
          "round": 4,
          "position": 19,
          "points": 0,
          "cumulativePoints": 0
        },
        {
          "round": 5,
          "position": 22,
          "points": 0,
          "cumulativePoints": 0
        },
        {
          "round": 6,
          "position": 15,
          "points": 0,
          "grid": 22,
          "cumulativePoints": 0
        },
        {
          "round": 7,
          "position": 19,
          "points": 0,
          "cumulativePoints": 0
        },
        {
          "round": 8,
          "position": 17,
          "points": 0,
          "cumulativePoints": 0,
          "grid": null
        }
      ],
      "photo": "/drivers/per.png"
    },
    {
      "id": "STR",
      "name": "Lance Stroll",
      "number": 18,
      "team": "Aston Martin",
      "teamId": "aston-martin",
      "teamColor": "#229971",
      "results": [
          {
          "round": 1,
          "position": 22,
          "points": 0,
          "cumulativePoints": 0
        },
        {
          "round": 2,
          "position": 17,
          "points": 0,
          "grid": 22,
          "fastestLapTime": "1:25.410",
          "status": "+15 laps",
          "cumulativePoints": 0
        },
        {
          "round": 3,
          "position": 19,
          "points": 0,
          "cumulativePoints": 0
        },
        {
          "round": 4,
          "position": 18,
          "points": 0,
          "cumulativePoints": 0
        },
        {
          "round": 5,
          "position": 21,
          "points": 0,
          "cumulativePoints": 0
        },
        {
          "round": 6,
          "position": 18,
          "points": 0,
          "grid": 21,
          "status": "DNF",
          "cumulativePoints": 0
        },
        {
          "round": 7,
          "position": 22,
          "points": 0,
          "cumulativePoints": 0
        },
        {
          "round": 8,
          "position": 21,
          "points": 0,
          "cumulativePoints": 0,
          "grid": null,
          "status": "DNF"
        }
      ],
      "photo": "/drivers/str.png"
    },
    {
      "id": "ALO",
      "name": "Fernando Alonso",
      "number": 14,
      "team": "Aston Martin",
      "teamId": "aston-martin",
      "teamColor": "#229971",
      "results": [
        {
          "round": 1,
          "position": 17,
          "points": 0,
          "cumulativePoints": 0
        },
        {
          "round": 2,
          "position": 18,
          "points": 0,
          "grid": 17,
          "fastestLapTime": "1:25.713",
          "status": "DNF",
          "cumulativePoints": 0
        },
        {
          "round": 3,
          "position": 18,
          "points": 0,
          "cumulativePoints": 0
        },
        {
          "round": 4,
          "position": 17,
          "points": 0,
          "cumulativePoints": 0
        },
        {
          "round": 5,
          "position": 19,
          "points": 0,
          "cumulativePoints": 0
        },
        {
          "round": 6,
          "position": 17,
          "points": 0,
          "grid": 19,
          "status": "DNF",
          "cumulativePoints": 0
        },
        {
          "round": 7,
          "position": 21,
          "points": 0,
          "cumulativePoints": 0
        },
        {
          "round": 8,
          "position": 18,
          "points": 0,
          "cumulativePoints": 0,
          "grid": null
        }
      ],
      "photo": "/drivers/alo.png"
    },
    {
      "id": "BOT",
      "name": "Valtteri Bottas",
      "number": 77,
      "team": "Cadillac",
      "teamId": "cadillac",
      "teamColor": "#1D1D1B",
      "results": [
        {
          "round": 1,
          "position": 19,
          "points": 0,
          "cumulativePoints": 0
        },
        {
          "round": 2,
          "position": 19,
          "points": 0,
          "grid": 19,
          "fastestLapTime": "1:27.364",
          "status": "DNF",
          "cumulativePoints": 0
        },
        {
          "round": 3,
          "position": 20,
          "points": 0,
          "cumulativePoints": 0
        },
        {
          "round": 4,
          "position": 21,
          "points": 0,
          "cumulativePoints": 0,
          "status": "DNF"
        },
        {
          "round": 5,
          "position": 20,
          "points": 0,
          "cumulativePoints": 0
        },
        {
          "round": 6,
          "position": 13,
          "points": 0,
          "grid": 20,
          "cumulativePoints": 0
        },
        {
          "round": 7,
          "position": 20,
          "points": 0,
          "cumulativePoints": 0
        },
        {
          "round": 8,
          "position": 19,
          "points": 0,
          "cumulativePoints": 0,
          "grid": null
        }
      ],
      "photo": "/drivers/bot.png"
    },
    {
      "id": "HAD",
      "name": "Isack Hadjar",
      "number": 6,
      "team": "Red Bull Racing",
      "teamId": "red-bull",
      "teamColor": "#3671C6",
      "results": [
        {
          "round": 1,
          "position": 3,
          "points": 0,
          "cumulativePoints": 0
        },
        {
          "round": 2,
          "position": 20,
          "points": 0,
          "grid": 3,
          "fastestLapTime": "1:25.239",
          "status": "DNF",
          "cumulativePoints": 0
        },
        {
          "round": 3,
          "position": 10,
          "points": 0,
          "cumulativePoints": 0
        },
        {
          "round": 4,
          "position": 15,
          "points": 0,
          "cumulativePoints": 0
        },
        {
          "round": 5,
          "position": 9,
          "points": 0,
          "cumulativePoints": 0
        },
        {
          "round": 6,
          "position": 8,
          "points": 4,
          "grid": 9,
          "cumulativePoints": 4
        },
        {
          "round": 7,
          "position": 8,
          "points": 0,
          "cumulativePoints": 4
        },
        {
          "round": 8,
          "position": 12,
          "points": 0,
          "cumulativePoints": 4,
          "grid": null
        }
      ],
      "photo": "/drivers/had.png"
    },
    {
      "id": "HUL",
      "name": "Nico Hulkenberg",
      "number": 27,
      "team": "Audi",
      "teamId": "sauber",
      "teamColor": "#52E252",
      "results": [
        {
          "round": 1,
          "position": 11,
          "points": 0,
          "cumulativePoints": 0
        },
        {
          "round": 2,
          "position": 22,
          "points": 0,
          "grid": 11,
          "status": "DNS",
          "cumulativePoints": 0
        },
        {
          "round": 3,
          "position": 11,
          "points": 0,
          "cumulativePoints": 0
        },
        {
          "round": 4,
          "position": 20,
          "points": 0,
          "cumulativePoints": 0,
          "status": "DNF"
        },
        {
          "round": 5,
          "position": 11,
          "points": 0,
          "cumulativePoints": 0
        },
        {
          "round": 6,
          "position": 11,
          "points": 0,
          "grid": 11,
          "cumulativePoints": 0
        },
        {
          "round": 7,
          "position": 13,
          "points": 0,
          "cumulativePoints": 0
        },
        {
          "round": 8,
          "position": 11,
          "points": 0,
          "cumulativePoints": 0,
          "grid": null
        }
      ],
      "photo": "/drivers/hul.png"
    }
  ],
  "constructors": [
    {
      "name": "Mercedes",
      "id": "mercedes",
      "color": "#27F4D2",
      "points": 135
    },
    {
      "name": "Ferrari",
      "id": "ferrari",
      "color": "#E8002D",
      "points": 90
    },
    {
      "name": "McLaren",
      "id": "mclaren",
      "color": "#FF8000",
      "points": 46
    },
    {
      "name": "Red Bull Racing",
      "id": "red-bull",
      "color": "#3671C6",
      "points": 16
    },
    {
      "name": "Haas",
      "id": "haas",
      "color": "#B6BABD",
      "points": 18
    },
    {
      "name": "Racing Bulls",
      "id": "racing-bulls",
      "color": "#6692FF",
      "points": 14
    },
    {
      "name": "Sauber",
      "id": "sauber",
      "color": "#52E252",
      "points": 2
    },
    {
      "name": "Alpine",
      "id": "alpine",
      "color": "#FF87BC",
      "points": 16
    },
    {
      "name": "Williams",
      "id": "williams",
      "color": "#1868DB",
      "points": 2
    },
    {
      "name": "Cadillac",
      "id": "cadillac",
      "color": "#1D1D1B",
      "points": 0
    },
    {
      "name": "Aston Martin",
      "id": "aston-martin",
      "color": "#229971",
      "points": 0
    }
  ],
  "teams": [
    {
      "id": "mercedes",
      "name": "Mercedes",
      "color": "#27F4D2",
      "abbr": "MER",
      "logo": "/teams/mercedes.png"
    },
    {
      "id": "ferrari",
      "name": "Ferrari",
      "color": "#E8002D",
      "abbr": "FER",
      "logo": "/teams/ferrari.png"
    },
    {
      "id": "mclaren",
      "name": "McLaren",
      "color": "#FF8000",
      "abbr": "MCL",
      "logo": "/teams/mclaren.png"
    },
    {
      "id": "red-bull",
      "name": "Red Bull Racing",
      "color": "#3671C6",
      "abbr": "RBR",
      "logo": "/teams/red-bull.png"
    },
    {
      "id": "haas",
      "name": "Haas",
      "color": "#B6BABD",
      "abbr": "HAS",
      "logo": "/teams/haas.png"
    },
    {
      "id": "racing-bulls",
      "name": "Racing Bulls",
      "color": "#6692FF",
      "abbr": "RCB",
      "logo": "/teams/racing-bulls.png"
    },
    {
      "id": "sauber",
      "name": "Audi",
      "color": "#52E252",
      "abbr": "SAU",
      "logo": "/teams/audi.png"
    },
    {
      "id": "alpine",
      "name": "Alpine",
      "color": "#FF87BC",
      "abbr": "ALP",
      "logo": "/teams/alpine.png"
    },
    {
      "id": "williams",
      "name": "Williams",
      "color": "#1868DB",
      "abbr": "WIL",
      "logo": "/teams/williams.png"
    },
    {
      "id": "cadillac",
      "name": "Cadillac",
      "color": "#1D1D1B",
      "abbr": "CAD",
      "logo": "/teams/cadillac.png"
    },
    {
      "id": "aston-martin",
      "name": "Aston Martin",
      "color": "#229971",
      "abbr": "AMR",
      "logo": "/teams/aston-martin.png"
    }
  ]
}